<?xml version="1.0" encoding="utf-8" ?>
<dwsync>
<file name="bottom_left.gif" server="C:/wamp/www/alfa/" local="130204399177968750" remote="130204399170000000" Dst="2" />
<file name="bottom_mid.gif" server="C:/wamp/www/alfa/" local="130204399178281250" remote="130204399170000000" Dst="2" />
<file name="bottom_right.gif" server="C:/wamp/www/alfa/" local="130204399178437500" remote="130204399170000000" Dst="2" />
<file name="bottom_right_resize.gif" server="C:/wamp/www/alfa/" local="130204399177968750" remote="130204399170000000" Dst="2" />
<file name="center_left.gif" server="C:/wamp/www/alfa/" local="130204399178125000" remote="130204399170000000" Dst="2" />
<file name="center_right.gif" server="C:/wamp/www/alfa/" local="130204399177812500" remote="130204399170000000" Dst="2" />
<file name="clear.gif" server="C:/wamp/www/alfa/" local="130204399178125000" remote="130204399170000000" Dst="2" />
<file name="close.gif" server="C:/wamp/www/alfa/" local="130204399178593750" remote="130204399170000000" Dst="2" />
<file name="inspect.gif" server="C:/wamp/www/alfa/" local="130204399178593750" remote="130204399170000000" Dst="2" />
<file name="maximize.gif" server="C:/wamp/www/alfa/" local="130204399178125000" remote="130204399170000000" Dst="2" />
<file name="minimize.gif" server="C:/wamp/www/alfa/" local="130204399177968750" remote="130204399170000000" Dst="2" />
<file name="overlay.png" server="C:/wamp/www/alfa/" local="130204399178437500" remote="130204399170000000" Dst="2" />
<file name="resize.gif" server="C:/wamp/www/alfa/" local="130204399178437500" remote="130204399170000000" Dst="2" />
<file name="sizer.gif" server="C:/wamp/www/alfa/" local="130204399178281250" remote="130204399170000000" Dst="2" />
<file name="top_left.gif" server="C:/wamp/www/alfa/" local="130204399177812500" remote="130204399170000000" Dst="2" />
<file name="top_mid.gif" server="C:/wamp/www/alfa/" local="130204399178125000" remote="130204399170000000" Dst="2" />
<file name="top_right.gif" server="C:/wamp/www/alfa/" local="130204399178281250" remote="130204399170000000" Dst="2" />
<file name="bottom_left.gif" server="C:/wamp/www/CasaGestion/" local="130204399177968750" remote="130204399170000000" Dst="2" />
<file name="bottom_mid.gif" server="C:/wamp/www/CasaGestion/" local="130204399178281250" remote="130204399170000000" Dst="2" />
<file name="bottom_right.gif" server="C:/wamp/www/CasaGestion/" local="130204399178437500" remote="130204399170000000" Dst="2" />
<file name="bottom_right_resize.gif" server="C:/wamp/www/CasaGestion/" local="130204399177968750" remote="130204399170000000" Dst="2" />
<file name="center_left.gif" server="C:/wamp/www/CasaGestion/" local="130204399178125000" remote="130204399170000000" Dst="2" />
<file name="center_right.gif" server="C:/wamp/www/CasaGestion/" local="130204399177812500" remote="130204399170000000" Dst="2" />
<file name="clear.gif" server="C:/wamp/www/CasaGestion/" local="130204399178125000" remote="130204399170000000" Dst="2" />
<file name="close.gif" server="C:/wamp/www/CasaGestion/" local="130204399178593750" remote="130204399170000000" Dst="2" />
<file name="inspect.gif" server="C:/wamp/www/CasaGestion/" local="130204399178593750" remote="130204399170000000" Dst="2" />
<file name="maximize.gif" server="C:/wamp/www/CasaGestion/" local="130204399178125000" remote="130204399170000000" Dst="2" />
<file name="minimize.gif" server="C:/wamp/www/CasaGestion/" local="130204399177968750" remote="130204399170000000" Dst="2" />
<file name="overlay.png" server="C:/wamp/www/CasaGestion/" local="130204399178437500" remote="130204399170000000" Dst="2" />
<file name="resize.gif" server="C:/wamp/www/CasaGestion/" local="130204399178437500" remote="130204399170000000" Dst="2" />
<file name="sizer.gif" server="C:/wamp/www/CasaGestion/" local="130204399178281250" remote="130204399170000000" Dst="2" />
<file name="top_left.gif" server="C:/wamp/www/CasaGestion/" local="130204399177812500" remote="130204399170000000" Dst="2" />
<file name="top_mid.gif" server="C:/wamp/www/CasaGestion/" local="130204399178125000" remote="130204399170000000" Dst="2" />
<file name="top_right.gif" server="C:/wamp/www/CasaGestion/" local="130204399178281250" remote="130204399170000000" Dst="2" />
<file name="bottom_left.gif" server="C:/wamp/www/casa/" local="130204399177968750" remote="130204399170000000" Dst="2" />
<file name="bottom_mid.gif" server="C:/wamp/www/casa/" local="130204399178281250" remote="130204399170000000" Dst="2" />
<file name="bottom_right.gif" server="C:/wamp/www/casa/" local="130204399178437500" remote="130204399170000000" Dst="2" />
<file name="bottom_right_resize.gif" server="C:/wamp/www/casa/" local="130204399177968750" remote="130204399170000000" Dst="2" />
<file name="center_left.gif" server="C:/wamp/www/casa/" local="130204399178125000" remote="130204399170000000" Dst="2" />
<file name="center_right.gif" server="C:/wamp/www/casa/" local="130204399177812500" remote="130204399170000000" Dst="2" />
<file name="clear.gif" server="C:/wamp/www/casa/" local="130204399178125000" remote="130204399170000000" Dst="2" />
<file name="close.gif" server="C:/wamp/www/casa/" local="130204399178593750" remote="130204399170000000" Dst="2" />
<file name="inspect.gif" server="C:/wamp/www/casa/" local="130204399178593750" remote="130204399170000000" Dst="2" />
<file name="maximize.gif" server="C:/wamp/www/casa/" local="130204399178125000" remote="130204399170000000" Dst="2" />
<file name="minimize.gif" server="C:/wamp/www/casa/" local="130204399177968750" remote="130204399170000000" Dst="2" />
<file name="overlay.png" server="C:/wamp/www/casa/" local="130204399178437500" remote="130204399170000000" Dst="2" />
<file name="resize.gif" server="C:/wamp/www/casa/" local="130204399178437500" remote="130204399170000000" Dst="2" />
<file name="sizer.gif" server="C:/wamp/www/casa/" local="130204399178281250" remote="130204399170000000" Dst="2" />
<file name="top_left.gif" server="C:/wamp/www/casa/" local="130204399177812500" remote="130204399170000000" Dst="2" />
<file name="top_mid.gif" server="C:/wamp/www/casa/" local="130204399178125000" remote="130204399170000000" Dst="2" />
<file name="top_right.gif" server="C:/wamp/www/casa/" local="130204399178281250" remote="130204399170000000" Dst="2" />
<file name="bottom_left.gif" server="C:/wamp/www/sp_www/" local="130204399177968750" remote="130204399170000000" Dst="2" />
<file name="bottom_mid.gif" server="C:/wamp/www/sp_www/" local="130204399178281250" remote="130204399170000000" Dst="2" />
<file name="bottom_right.gif" server="C:/wamp/www/sp_www/" local="130204399178437500" remote="130204399170000000" Dst="2" />
<file name="bottom_right_resize.gif" server="C:/wamp/www/sp_www/" local="130204399177968750" remote="130204399170000000" Dst="2" />
<file name="center_left.gif" server="C:/wamp/www/sp_www/" local="130204399178125000" remote="130204399170000000" Dst="2" />
<file name="center_right.gif" server="C:/wamp/www/sp_www/" local="130204399177812500" remote="130204399170000000" Dst="2" />
<file name="clear.gif" server="C:/wamp/www/sp_www/" local="130204399178125000" remote="130204399170000000" Dst="2" />
<file name="close.gif" server="C:/wamp/www/sp_www/" local="130204399178593750" remote="130204399170000000" Dst="2" />
<file name="inspect.gif" server="C:/wamp/www/sp_www/" local="130204399178593750" remote="130204399170000000" Dst="2" />
<file name="maximize.gif" server="C:/wamp/www/sp_www/" local="130204399178125000" remote="130204399170000000" Dst="2" />
<file name="minimize.gif" server="C:/wamp/www/sp_www/" local="130204399177968750" remote="130204399170000000" Dst="2" />
<file name="overlay.png" server="C:/wamp/www/sp_www/" local="130204399178437500" remote="130204399170000000" Dst="2" />
<file name="resize.gif" server="C:/wamp/www/sp_www/" local="130204399178437500" remote="130204399170000000" Dst="2" />
<file name="sizer.gif" server="C:/wamp/www/sp_www/" local="130204399178281250" remote="130204399170000000" Dst="2" />
<file name="top_left.gif" server="C:/wamp/www/sp_www/" local="130204399177812500" remote="130204399170000000" Dst="2" />
<file name="top_mid.gif" server="C:/wamp/www/sp_www/" local="130204399178125000" remote="130204399170000000" Dst="2" />
<file name="top_right.gif" server="C:/wamp/www/sp_www/" local="130204399178281250" remote="130204399170000000" Dst="2" />
<file name="bottom_left.gif" server="C:/wamp/www/proy_act/" local="130204399177968750" remote="130204399170000000" Dst="2" />
<file name="bottom_mid.gif" server="C:/wamp/www/proy_act/" local="130204399178281250" remote="130204399170000000" Dst="2" />
<file name="bottom_right.gif" server="C:/wamp/www/proy_act/" local="130204399178437500" remote="130204399170000000" Dst="2" />
<file name="bottom_right_resize.gif" server="C:/wamp/www/proy_act/" local="130204399177968750" remote="130204399170000000" Dst="2" />
<file name="center_left.gif" server="C:/wamp/www/proy_act/" local="130204399178125000" remote="130204399170000000" Dst="2" />
<file name="center_right.gif" server="C:/wamp/www/proy_act/" local="130204399177812500" remote="130204399170000000" Dst="2" />
<file name="clear.gif" server="C:/wamp/www/proy_act/" local="130204399178125000" remote="130204399170000000" Dst="2" />
<file name="close.gif" server="C:/wamp/www/proy_act/" local="130204399178593750" remote="130204399170000000" Dst="2" />
<file name="inspect.gif" server="C:/wamp/www/proy_act/" local="130204399178593750" remote="130204399170000000" Dst="2" />
<file name="maximize.gif" server="C:/wamp/www/proy_act/" local="130204399178125000" remote="130204399170000000" Dst="2" />
<file name="minimize.gif" server="C:/wamp/www/proy_act/" local="130204399177968750" remote="130204399170000000" Dst="2" />
<file name="overlay.png" server="C:/wamp/www/proy_act/" local="130204399178437500" remote="130204399170000000" Dst="2" />
<file name="resize.gif" server="C:/wamp/www/proy_act/" local="130204399178437500" remote="130204399170000000" Dst="2" />
<file name="sizer.gif" server="C:/wamp/www/proy_act/" local="130204399178281250" remote="130204399170000000" Dst="2" />
<file name="top_left.gif" server="C:/wamp/www/proy_act/" local="130204399177812500" remote="130204399170000000" Dst="2" />
<file name="top_mid.gif" server="C:/wamp/www/proy_act/" local="130204399178125000" remote="130204399170000000" Dst="2" />
<file name="top_right.gif" server="C:/wamp/www/proy_act/" local="130204399178281250" remote="130204399170000000" Dst="2" />
<file name="bottom_left.gif" server="C:/wamp/www/sp_w/" local="130204399177968750" remote="130204399170000000" Dst="2" />
<file name="bottom_mid.gif" server="C:/wamp/www/sp_w/" local="130204399178281250" remote="130204399170000000" Dst="2" />
<file name="bottom_right.gif" server="C:/wamp/www/sp_w/" local="130204399178437500" remote="130204399170000000" Dst="2" />
<file name="bottom_right_resize.gif" server="C:/wamp/www/sp_w/" local="130204399177968750" remote="130204399170000000" Dst="2" />
<file name="center_left.gif" server="C:/wamp/www/sp_w/" local="130204399178125000" remote="130204399170000000" Dst="2" />
<file name="center_right.gif" server="C:/wamp/www/sp_w/" local="130204399177812500" remote="130204399170000000" Dst="2" />
<file name="clear.gif" server="C:/wamp/www/sp_w/" local="130204399178125000" remote="130204399170000000" Dst="2" />
<file name="close.gif" server="C:/wamp/www/sp_w/" local="130204399178593750" remote="130204399170000000" Dst="2" />
<file name="inspect.gif" server="C:/wamp/www/sp_w/" local="130204399178593750" remote="130204399170000000" Dst="2" />
<file name="maximize.gif" server="C:/wamp/www/sp_w/" local="130204399178125000" remote="130204399170000000" Dst="2" />
<file name="minimize.gif" server="C:/wamp/www/sp_w/" local="130204399177968750" remote="130204399170000000" Dst="2" />
<file name="overlay.png" server="C:/wamp/www/sp_w/" local="130204399178437500" remote="130204399170000000" Dst="2" />
<file name="resize.gif" server="C:/wamp/www/sp_w/" local="130204399178437500" remote="130204399170000000" Dst="2" />
<file name="sizer.gif" server="C:/wamp/www/sp_w/" local="130204399178281250" remote="130204399170000000" Dst="2" />
<file name="top_left.gif" server="C:/wamp/www/sp_w/" local="130204399177812500" remote="130204399170000000" Dst="2" />
<file name="top_mid.gif" server="C:/wamp/www/sp_w/" local="130204399178125000" remote="130204399170000000" Dst="2" />
<file name="top_right.gif" server="C:/wamp/www/sp_w/" local="130204399178281250" remote="130204399170000000" Dst="2" />
</dwsync>